gef_file_to_map-0.2.0.dist-info/METADATA
gef_file_to_map-0.2.0.dist-info/WHEEL
gef_file_to_map-0.2.0.dist-info/licenses/LICENSE
gef_file_to_map/__init__.py
gef_file_to_map/gef_file_to_map.abi3.so
gef_file_to_map-0.2.0.dist-info/RECORD
