Metadata-Version: 2.4
Name: gef-file-to-map
Version: 0.2.0
Classifier: Programming Language :: Rust
Classifier: Programming Language :: Python :: Implementation :: CPython
Classifier: Programming Language :: Python :: Implementation :: PyPy
License-File: LICENSE
Summary: Utility library for parsing .gef files
Keywords: gef,pygef
Author-email: Thomas Versteeg <t.versteeg@cemsbv.io>
Requires-Python: >=3.7
Project-URL: repository, https://github.com/cemsbv/gef-file-to-map
